LICENSE
README.rst
setup.py
chilexpress/connector.py
chilexpress/handler.py
chilexpress/settings.py
corona_chilexpress.egg-info/PKG-INFO
corona_chilexpress.egg-info/SOURCES.txt
corona_chilexpress.egg-info/dependency_links.txt
corona_chilexpress.egg-info/requires.txt
corona_chilexpress.egg-info/top_level.txt