Metadata-Version: 2.1
Name: corona-chilexpress
Version: 1.0.0
Summary: Django Chilexpress integration
Home-page: https://gitlab.com/corona-projects/python-libraries/django-chilexpress/
Author: Corona Development Team
Author-email: rolguin@corona.cl
License: MIT
Platform: UNKNOWN
Requires-Python: >=3.7
License-File: LICENSE
